freesurfer_pp
