Metadata-Version: 1.0
Name: freesurfer-pp
Version: 2.0.1
Summary: A simple/dummy app that simulates a FreeSurfer run
Home-page: https://github.com/FNNDSC/pl-freesurfer_pp
Author: Rudolph Pienaar
Author-email: rudolph.pienaar@gmail.com
License: MIT
Platform: UNKNOWN
